playground/__main__.py
playground/resources/playground_compose.yaml
playground/resources/mysql/Chinook_Mysql.sql
playground/resources/oracle/Chinook_Oracle.sql
playground/resources/postgres/Chinook_Postgres.sql
localstack_playground-0.1.5.dist-info/METADATA
localstack_playground-0.1.5.dist-info/WHEEL
localstack_playground-0.1.5.dist-info/entry_points.txt
localstack_playground-0.1.5.dist-info/licenses/LICENSE
localstack_playground-0.1.5.dist-info/RECORD
